aiosteampy/__init__.py
aiosteampy/client.py
aiosteampy/constants.py
aiosteampy/exceptions.py
aiosteampy/ext/__init__.py
aiosteampy/ext/converter.py
aiosteampy/ext/user_agents.py
aiosteampy/helpers.py
aiosteampy/mixins/__init__.py
aiosteampy/mixins/confirmation.py
aiosteampy/mixins/guard.py
aiosteampy/mixins/http.py
aiosteampy/mixins/login.py
aiosteampy/mixins/market.py
aiosteampy/mixins/profile.py
aiosteampy/mixins/public.py
aiosteampy/mixins/trade.py
aiosteampy/mixins/web_api.py
aiosteampy/models.py
aiosteampy/typed.py
aiosteampy/utils.py
aiosteampy-0.7.18.dist-info/METADATA
aiosteampy-0.7.18.dist-info/WHEEL
aiosteampy-0.7.18.dist-info/licenses/LICENSE
aiosteampy-0.7.18.dist-info/RECORD
