Metadata-Version: 2.4
Name: aiosteampy
Version: 0.7.18
Summary: Trade and interact with steam market, webapi, guard
License-Expression: MIT
License-File: LICENSE
Keywords: steam,trade,steamguard,asyncio,steam-market
Author: Dmytro Tkachenko
Author-email: itsme@somespecial.one
Requires-Python: >=3.10
Classifier: Framework :: AsyncIO
Classifier: Development Status :: 4 - Beta
Classifier: Intended Audience :: Developers
Classifier: Intended Audience :: Information Technology
Classifier: Topic :: Software Development
Classifier: Topic :: Software Development :: Libraries
Classifier: Topic :: Software Development :: Libraries :: Python Modules
Classifier: Operating System :: OS Independent
Classifier: Programming Language :: Python
Classifier: Programming Language :: Python :: 3
Classifier: Programming Language :: Python :: 3 :: Only
Classifier: Programming Language :: Python :: 3.10
Classifier: Programming Language :: Python :: 3.11
Classifier: Programming Language :: Python :: 3.12
Classifier: Programming Language :: Python :: 3.13
Classifier: Typing :: Typed
Provides-Extra: all
Provides-Extra: converter
Provides-Extra: socks
Requires-Dist: aenum (>=3.1.2,<4.0.0)
Requires-Dist: aiohttp (>=3.11,<4.0)
Requires-Dist: aiohttp-socks (>=0.8.4,<1.0.0) ; extra == "all"
Requires-Dist: aiohttp-socks (>=0.8.4,<1.0.0) ; extra == "socks"
Requires-Dist: croniter (>=2.0,<4.0) ; extra == "all"
Requires-Dist: croniter (>=2.0,<4.0) ; extra == "converter"
Requires-Dist: rsa (>=4.8,<5.0) ; python_version >= "3.10" and python_version < "4"
Project-URL: Bug Tracker, https://github.com/somespecialone/aiosteampy/issues
Project-URL: Documentation, https://aiosteampy.somespecial.one
Project-URL: Homepage, https://github.com/somespecialone/aiosteampy
Project-URL: Repository, https://github.com/somespecialone/aiosteampy
